simple_voice_chat/__init__.py
simple_voice_chat/__main__.py
simple_voice_chat/index.html
simple_voice_chat/simple_voice_chat.py
simple_voice_chat/utils/__init__.py
simple_voice_chat/utils/config.py
simple_voice_chat/utils/env.py
simple_voice_chat/utils/llms.py
simple_voice_chat/utils/logging_config.py
simple_voice_chat/utils/misc.py
simple_voice_chat/utils/stt.py
simple_voice_chat/utils/tts.py
simple_voice_chat-4.2.3.dist-info/licenses/LICENSE
simple_voice_chat-4.2.3.dist-info/METADATA
simple_voice_chat-4.2.3.dist-info/WHEEL
simple_voice_chat-4.2.3.dist-info/entry_points.txt
simple_voice_chat-4.2.3.dist-info/top_level.txt
simple_voice_chat-4.2.3.dist-info/RECORD
