Metadata-Version: 2.4
Name: simple-voice-chat
Version: 4.2.3
Summary: A simple voice chat interface using configurable LLM, STT, and TTS providers.
Home-page: https://github.com/thiswillbeyourgithub/simple_voice_chat
Author: thiswillbeyourgithub
Project-URL: Bug Reports, https://github.com/thiswillbeyourgithub/simple_voice_chat/issues
Project-URL: Source, https://github.com/thiswillbeyourgithub/simple_voice_chat
Keywords: voice chat,llm,stt,tts,ai,chatbot,fastrtc,openai
Classifier: Programming Language :: Python :: 3
Classifier: Programming Language :: Python :: 3.9
Classifier: Programming Language :: Python :: 3.10
Classifier: Programming Language :: Python :: 3.11
Classifier: Programming Language :: Python :: 3.12
Classifier: Operating System :: OS Independent
Classifier: Topic :: Communications :: Chat
Classifier: Topic :: Multimedia :: Sound/Audio :: Speech
Classifier: Topic :: Scientific/Engineering :: Artificial Intelligence
Requires-Python: >=3.9
License-File: LICENSE
Requires-Dist: click>=8.0
Requires-Dist: qtpy>=2.4.3
Requires-Dist: filelock>=3.18.0
Requires-Dist: fastrtc[tts,vad]>=0.0.23
Requires-Dist: openai>=1.76.0
Requires-Dist: twilio>=9.5.2
Requires-Dist: python-dotenv>=1.1.0
Requires-Dist: pywebview>=5.4
Requires-Dist: PyQt6>=6.9.0
Requires-Dist: PyQt6-WebEngine>=6.9.0
Requires-Dist: psutil>=7.0.0
Requires-Dist: numpy>=2.2.5
Requires-Dist: fastapi>=0.115.12
Requires-Dist: uvicorn[standard]>=0.34.2
Requires-Dist: litellm>=1.67.2
Requires-Dist: loguru>=0.7.3
Requires-Dist: platformdirs>=4.3.7
Requires-Dist: google-genai>=1.14.0
Dynamic: author
Dynamic: classifier
Dynamic: description
Dynamic: description-content-type
Dynamic: home-page
Dynamic: keywords
Dynamic: license-file
Dynamic: project-url
Dynamic: requires-dist
Dynamic: requires-python
Dynamic: summary
